{"matches": [{"num": 1, "date": "Jun 11, 2026", "time": "19:00", "home": "Mexico", "away": "South Africa", "group": "A", "fifa_h": 1681.0, "fifa_a": 1429.7, "lh": 2.42, "la": 0.83, "pH": 0.72, "pD": 0.176, "pA": 0.105, "mode": [2, 0], "mode_p": 0.114, "rec": [2, 0], "rec_ev": 1.046, "expert": [3, 1], "top": [{"h": 2, "a": 0, "p": 0.1143}, {"h": 2, "a": 1, "p": 0.0945}, {"h": 3, "a": 0, "p": 0.0921}, {"h": 1, "a": 0, "p": 0.0898}, {"h": 1, "a": 1, "p": 0.0829}, {"h": 3, "a": 1, "p": 0.0762}]}, {"num": 2, "date": "Jun 12, 2026", "time": "02:00", "home": "Korea Republic", "away": "Czech Republic", "group": "A", "fifa_h": 1588.7, "fifa_a": 1501.4, "lh": 1.29, "la": 1.05, "pH": 0.412, "pD": 0.294, "pA": 0.294, "mode": [1, 1], "mode_p": 0.138, "rec": [1, 0], "rec_ev": 0.75, "expert": [1, 1], "top": [{"h": 1, "a": 1, "p": 0.1383}, {"h": 1, "a": 0, "p": 0.1163}, {"h": 0, "a": 0, "p": 0.1039}, {"h": 0, "a": 1, "p": 0.0932}, {"h": 2, "a": 1, "p": 0.0842}, {"h": 2, "a": 0, "p": 0.0801}]}, {"num": 3, "date": "Jun 12, 2026", "time": "19:00", "home": "Canada", "away": "Bosnia and Herzegovina", "group": "B", "fifa_h": 1556.5, "fifa_a": 1385.8, "lh": 1.85, "la": 0.93, "pH": 0.583, "pD": 0.237, "pA": 0.18, "mode": [1, 1], "mode_p": 0.113, "rec": [1, 0], "rec_ev": 0.931, "expert": [2, 1], "top": [{"h": 1, "a": 1, "p": 0.1131}, {"h": 1, "a": 0, "p": 0.1078}, {"h": 2, "a": 0, "p": 0.1058}, {"h": 2, "a": 1, "p": 0.0989}, {"h": 0, "a": 0, "p": 0.068}, {"h": 3, "a": 0, "p": 0.0654}]}, {"num": 4, "date": "Jun 13, 2026", "time": "01:00", "home": "United States", "away": "Paraguay", "group": "D", "fifa_h": 1673.1, "fifa_a": 1503.5, "lh": 1.86, "la": 0.94, "pH": 0.582, "pD": 0.237, "pA": 0.181, "mode": [1, 1], "mode_p": 0.113, "rec": [1, 0], "rec_ev": 0.927, "expert": [2, 1], "top": [{"h": 1, "a": 1, "p": 0.1128}, {"h": 1, "a": 0, "p": 0.1063}, {"h": 2, "a": 0, "p": 0.1049}, {"h": 2, "a": 1, "p": 0.099}, {"h": 0, "a": 0, "p": 0.067}, {"h": 3, "a": 0, "p": 0.065}]}, {"num": 5, "date": "Jun 14, 2026", "time": "01:00", "home": "Haiti", "away": "Scotland", "group": "C", "fifa_h": 1291.7, "fifa_a": 1498.3, "lh": 0.45, "la": 2.36, "pH": 0.05, "pD": 0.151, "pA": 0.8, "mode": [0, 2], "mode_p": 0.169, "rec": [0, 2], "rec_ev": 1.205, "expert": [0, 3], "top": [{"h": 0, "a": 2, "p": 0.1689}, {"h": 0, "a": 1, "p": 0.1391}, {"h": 0, "a": 3, "p": 0.133}, {"h": 0, "a": 4, "p": 0.0786}, {"h": 1, "a": 2, "p": 0.0752}, {"h": 1, "a": 1, "p": 0.0675}]}, {"num": 6, "date": "Jun 14, 2026", "time": "04:00", "home": "Australia", "away": "Turkey", "group": "D", "fifa_h": 1580.7, "fifa_a": 1599.0, "lh": 0.7, "la": 1.65, "pH": 0.15, "pD": 0.255, "pA": 0.596, "mode": [0, 1], "mode_p": 0.15, "rec": [0, 1], "rec_ev": 1.007, "expert": [0, 2], "top": [{"h": 0, "a": 1, "p": 0.1503}, {"h": 0, "a": 2, "p": 0.1296}, {"h": 1, "a": 1, "p": 0.1168}, {"h": 0, "a": 0, "p": 0.1016}, {"h": 1, "a": 2, "p": 0.091}, {"h": 0, "a": 3, "p": 0.0714}]}, {"num": 7, "date": "Jun 13, 2026", "time": "22:00", "home": "Brazil", "away": "Morocco", "group": "C", "fifa_h": 1761.2, "fifa_a": 1755.9, "lh": 0.76, "la": 0.74, "pH": 0.313, "pD": 0.382, "pA": 0.305, "mode": [0, 0], "mode_p": 0.23, "rec": [0, 0], "rec_ev": 0.995, "expert": [0, 0], "top": [{"h": 0, "a": 0, "p": 0.2304}, {"h": 1, "a": 0, "p": 0.1614}, {"h": 0, "a": 1, "p": 0.1581}, {"h": 1, "a": 1, "p": 0.1331}, {"h": 2, "a": 0, "p": 0.064}, {"h": 0, "a": 2, "p": 0.0616}]}, {"num": 8, "date": "Jun 13, 2026", "time": "19:00", "home": "Qatar", "away": "Switzerland", "group": "B", "fifa_h": 1455.0, "fifa_a": 1649.4, "lh": 0.45, "la": 2.34, "pH": 0.052, "pD": 0.154, "pA": 0.794, "mode": [0, 2], "mode_p": 0.168, "rec": [0, 2], "rec_ev": 1.198, "expert": [0, 3], "top": [{"h": 0, "a": 2, "p": 0.1678}, {"h": 0, "a": 1, "p": 0.1396}, {"h": 0, "a": 3, "p": 0.1309}, {"h": 0, "a": 4, "p": 0.0765}, {"h": 1, "a": 2, "p": 0.0763}, {"h": 1, "a": 1, "p": 0.0692}]}, {"num": 9, "date": "Jun 14, 2026", "time": "23:00", "home": "Ivory Coast", "away": "Ecuador", "group": "E", "fifa_h": 1533.0, "fifa_a": 1594.8, "lh": 1.09, "la": 1.26, "pH": 0.311, "pD": 0.295, "pA": 0.394, "mode": [1, 1], "mode_p": 0.139, "rec": [1, 1], "rec_ev": 0.728, "expert": [1, 1], "top": [{"h": 1, "a": 1, "p": 0.1389}, {"h": 0, "a": 1, "p": 0.1125}, {"h": 0, "a": 0, "p": 0.1035}, {"h": 1, "a": 0, "p": 0.0962}, {"h": 1, "a": 2, "p": 0.0825}, {"h": 0, "a": 2, "p": 0.0757}]}, {"num": 10, "date": "Jun 14, 2026", "time": "17:00", "home": "Germany", "away": "Curaçao", "group": "E", "fifa_h": 1730.4, "fifa_a": 1294.7, "lh": 3.57, "la": 0.18, "pH": 0.95, "pD": 0.045, "pA": 0.006, "mode": [3, 0], "mode_p": 0.184, "rec": [3, 0], "rec_ev": 1.349, "expert": [5, 0], "top": [{"h": 3, "a": 0, "p": 0.1839}, {"h": 4, "a": 0, "p": 0.1639}, {"h": 2, "a": 0, "p": 0.1547}, {"h": 5, "a": 0, "p": 0.1169}, {"h": 1, "a": 0, "p": 0.0858}, {"h": 6, "a": 0, "p": 0.0695}]}, {"num": 11, "date": "Jun 14, 2026", "time": "20:00", "home": "Netherlands", "away": "Japan", "group": "F", "fifa_h": 1757.9, "fifa_a": 1660.4, "lh": 1.78, "la": 1.06, "pH": 0.535, "pD": 0.247, "pA": 0.218, "mode": [1, 1], "mode_p": 0.117, "rec": [2, 1], "rec_ev": 0.865, "expert": [2, 1], "top": [{"h": 1, "a": 1, "p": 0.117}, {"h": 2, "a": 1, "p": 0.0981}, {"h": 1, "a": 0, "p": 0.0976}, {"h": 2, "a": 0, "p": 0.0926}, {"h": 0, "a": 0, "p": 0.0652}, {"h": 1, "a": 2, "p": 0.0585}]}, {"num": 12, "date": "Jun 15, 2026", "time": "02:00", "home": "Sweden", "away": "Tunisia", "group": "F", "fifa_h": 1514.8, "fifa_a": 1483.0, "lh": 1.21, "la": 0.67, "pH": 0.483, "pD": 0.319, "pA": 0.198, "mode": [1, 0], "mode_p": 0.177, "rec": [1, 0], "rec_ev": 0.923, "expert": [1, 0], "top": [{"h": 1, "a": 0, "p": 0.177}, {"h": 0, "a": 0, "p": 0.16}, {"h": 1, "a": 1, "p": 0.1312}, {"h": 2, "a": 0, "p": 0.1115}, {"h": 0, "a": 1, "p": 0.095}, {"h": 2, "a": 1, "p": 0.0748}]}, {"num": 13, "date": "Jun 15, 2026", "time": "22:00", "home": "Saudi Arabia", "away": "Uruguay", "group": "H", "fifa_h": 1421.4, "fifa_a": 1673.1, "lh": 0.38, "la": 1.97, "pH": 0.057, "pD": 0.19, "pA": 0.753, "mode": [0, 2], "mode_p": 0.186, "rec": [0, 1], "rec_ev": 1.202, "expert": [0, 2], "top": [{"h": 0, "a": 2, "p": 0.1861}, {"h": 0, "a": 1, "p": 0.1849}, {"h": 0, "a": 3, "p": 0.122}, {"h": 0, "a": 0, "p": 0.1004}, {"h": 1, "a": 1, "p": 0.0753}, {"h": 1, "a": 2, "p": 0.0699}]}, {"num": 14, "date": "Jun 15, 2026", "time": "16:00", "home": "Spain", "away": "Cape Verde", "group": "H", "fifa_h": 1876.4, "fifa_a": 1366.1, "lh": 3.23, "la": 0.18, "pH": 0.934, "pD": 0.058, "pA": 0.007, "mode": [3, 0], "mode_p": 0.189, "rec": [3, 0], "rec_ev": 1.341, "expert": [4, 0], "top": [{"h": 3, "a": 0, "p": 0.1889}, {"h": 2, "a": 0, "p": 0.1753}, {"h": 4, "a": 0, "p": 0.1527}, {"h": 1, "a": 0, "p": 0.1072}, {"h": 5, "a": 0, "p": 0.0987}, {"h": 6, "a": 0, "p": 0.0532}]}, {"num": 15, "date": "Jun 16, 2026", "time": "01:00", "home": "Iran", "away": "New Zealand", "group": "G", "fifa_h": 1615.3, "fifa_a": 1281.6, "lh": 1.63, "la": 0.26, "pH": 0.718, "pD": 0.23, "pA": 0.051, "mode": [1, 0], "mode_p": 0.242, "rec": [1, 0], "rec_ev": 1.258, "expert": [1, 0], "top": [{"h": 1, "a": 0, "p": 0.2416}, {"h": 2, "a": 0, "p": 0.2001}, {"h": 0, "a": 0, "p": 0.1544}, {"h": 3, "a": 0, "p": 0.1088}, {"h": 1, "a": 1, "p": 0.0685}, {"h": 2, "a": 1, "p": 0.0527}]}, {"num": 16, "date": "Jun 15, 2026", "time": "19:00", "home": "Belgium", "away": "Egypt", "group": "G", "fifa_h": 1734.7, "fifa_a": 1563.2, "lh": 1.87, "la": 0.5, "pH": 0.701, "pD": 0.214, "pA": 0.085, "mode": [1, 0], "mode_p": 0.17, "rec": [1, 0], "rec_ev": 1.135, "expert": [2, 0], "top": [{"h": 1, "a": 0, "p": 0.1696}, {"h": 2, "a": 0, "p": 0.1636}, {"h": 3, "a": 0, "p": 0.1021}, {"h": 0, "a": 0, "p": 0.0987}, {"h": 1, "a": 1, "p": 0.0926}, {"h": 2, "a": 1, "p": 0.0818}]}, {"num": 17, "date": "Jun 16, 2026", "time": "19:00", "home": "France", "away": "Senegal", "group": "I", "fifa_h": 1877.3, "fifa_a": 1689.0, "lh": 1.91, "la": 0.95, "pH": 0.594, "pD": 0.231, "pA": 0.175, "mode": [1, 1], "mode_p": 0.11, "rec": [1, 0], "rec_ev": 0.935, "expert": [2, 1], "top": [{"h": 1, "a": 1, "p": 0.1101}, {"h": 2, "a": 0, "p": 0.1051}, {"h": 1, "a": 0, "p": 0.1036}, {"h": 2, "a": 1, "p": 0.0993}, {"h": 3, "a": 0, "p": 0.067}, {"h": 0, "a": 0, "p": 0.0637}]}, {"num": 18, "date": "Jun 16, 2026", "time": "22:00", "home": "Iraq", "away": "Norway", "group": "I", "fifa_h": 1447.1, "fifa_a": 1550.9, "lh": 0.57, "la": 2.21, "pH": 0.077, "pD": 0.179, "pA": 0.744, "mode": [0, 2], "mode_p": 0.151, "rec": [0, 2], "rec_ev": 1.122, "expert": [0, 3], "top": [{"h": 0, "a": 2, "p": 0.1515}, {"h": 0, "a": 1, "p": 0.1325}, {"h": 0, "a": 3, "p": 0.1115}, {"h": 1, "a": 2, "p": 0.0867}, {"h": 1, "a": 1, "p": 0.0833}, {"h": 0, "a": 0, "p": 0.0669}]}, {"num": 19, "date": "Jun 17, 2026", "time": "01:00", "home": "Argentina", "away": "Algeria", "group": "J", "fifa_h": 1874.8, "fifa_a": 1564.3, "lh": 2.07, "la": 0.32, "pH": 0.787, "pD": 0.17, "pA": 0.043, "mode": [2, 0], "mode_p": 0.197, "rec": [1, 0], "rec_ev": 1.23, "expert": [2, 0], "top": [{"h": 2, "a": 0, "p": 0.1969}, {"h": 1, "a": 0, "p": 0.1864}, {"h": 3, "a": 0, "p": 0.136}, {"h": 0, "a": 0, "p": 0.0953}, {"h": 4, "a": 0, "p": 0.0705}, {"h": 1, "a": 1, "p": 0.0641}]}, {"num": 20, "date": "Jun 17, 2026", "time": "04:00", "home": "Austria", "away": "Jordan", "group": "J", "fifa_h": 1593.5, "fifa_a": 1391.5, "lh": 2.34, "la": 0.44, "pH": 0.799, "pD": 0.152, "pA": 0.05, "mode": [2, 0], "mode_p": 0.171, "rec": [2, 0], "rec_ev": 1.206, "expert": [3, 0], "top": [{"h": 2, "a": 0, "p": 0.1705}, {"h": 1, "a": 0, "p": 0.1417}, {"h": 3, "a": 0, "p": 0.1332}, {"h": 4, "a": 0, "p": 0.0781}, {"h": 2, "a": 1, "p": 0.0747}, {"h": 1, "a": 1, "p": 0.0676}]}, {"num": 21, "date": "Jun 17, 2026", "time": "23:00", "home": "Ghana", "away": "Panama", "group": "L", "fifa_h": 1346.3, "fifa_a": 1540.6, "lh": 1.36, "la": 1.44, "pH": 0.347, "pD": 0.267, "pA": 0.386, "mode": [1, 1], "mode_p": 0.126, "rec": [1, 2], "rec_ev": 0.671, "expert": [2, 1], "top": [{"h": 1, "a": 1, "p": 0.1264}, {"h": 1, "a": 2, "p": 0.0859}, {"h": 2, "a": 1, "p": 0.0808}, {"h": 0, "a": 1, "p": 0.0808}, {"h": 1, "a": 0, "p": 0.0757}, {"h": 0, "a": 0, "p": 0.0682}]}, {"num": 22, "date": "Jun 17, 2026", "time": "20:00", "home": "England", "away": "Croatia", "group": "L", "fifa_h": 1826.0, "fifa_a": 1717.1, "lh": 1.35, "la": 0.6, "pH": 0.544, "pD": 0.297, "pA": 0.159, "mode": [1, 0], "mode_p": 0.185, "rec": [1, 0], "rec_ev": 1.003, "expert": [1, 0], "top": [{"h": 1, "a": 0, "p": 0.1846}, {"h": 0, "a": 0, "p": 0.1485}, {"h": 2, "a": 0, "p": 0.1295}, {"h": 1, "a": 1, "p": 0.1223}, {"h": 0, "a": 1, "p": 0.0784}, {"h": 2, "a": 1, "p": 0.078}]}, {"num": 23, "date": "Jun 17, 2026", "time": "17:00", "home": "Portugal", "away": "DR Congo", "group": "K", "fifa_h": 1763.8, "fifa_a": 1478.3, "lh": 2.47, "la": 0.34, "pH": 0.839, "pD": 0.129, "pA": 0.032, "mode": [2, 0], "mode_p": 0.184, "rec": [2, 0], "rec_ev": 1.265, "expert": [3, 0], "top": [{"h": 2, "a": 0, "p": 0.1844}, {"h": 3, "a": 0, "p": 0.1521}, {"h": 1, "a": 0, "p": 0.146}, {"h": 4, "a": 0, "p": 0.0941}, {"h": 0, "a": 0, "p": 0.0633}, {"h": 2, "a": 1, "p": 0.0625}]}, {"num": 24, "date": "Jun 18, 2026", "time": "02:00", "home": "Uzbekistan", "away": "Colombia", "group": "K", "fifa_h": 1465.3, "fifa_a": 1693.1, "lh": 0.41, "la": 1.94, "pH": 0.065, "pD": 0.197, "pA": 0.738, "mode": [0, 1], "mode_p": 0.18, "rec": [0, 1], "rec_ev": 1.183, "expert": [0, 2], "top": [{"h": 0, "a": 1, "p": 0.1802}, {"h": 0, "a": 2, "p": 0.1791}, {"h": 0, "a": 3, "p": 0.1158}, {"h": 0, "a": 0, "p": 0.0999}, {"h": 1, "a": 1, "p": 0.0808}, {"h": 1, "a": 2, "p": 0.0739}]}, {"num": 25, "date": "Jun 18, 2026", "time": "16:00", "home": "Czech Republic", "away": "South Africa", "group": "A", "fifa_h": 1501.4, "fifa_a": 1429.7, "lh": 1.72, "la": 0.62, "pH": 0.633, "pD": 0.243, "pA": 0.124, "mode": [1, 0], "mode_p": 0.16, "rec": [1, 0], "rec_ev": 1.058, "expert": [2, 0], "top": [{"h": 1, "a": 0, "p": 0.1595}, {"h": 2, "a": 0, "p": 0.1423}, {"h": 1, "a": 1, "p": 0.1091}, {"h": 0, "a": 0, "p": 0.1026}, {"h": 2, "a": 1, "p": 0.0884}, {"h": 3, "a": 0, "p": 0.0815}]}, {"num": 26, "date": "Jun 18, 2026", "time": "19:00", "home": "Switzerland", "away": "Bosnia and Herzegovina", "group": "B", "fifa_h": 1649.4, "fifa_a": 1385.8, "lh": 1.53, "la": 0.35, "pH": 0.666, "pD": 0.256, "pA": 0.078, "mode": [1, 0], "mode_p": 0.227, "rec": [1, 0], "rec_ev": 1.19, "expert": [1, 0], "top": [{"h": 1, "a": 0, "p": 0.2274}, {"h": 2, "a": 0, "p": 0.1777}, {"h": 0, "a": 0, "p": 0.1568}, {"h": 3, "a": 0, "p": 0.0906}, {"h": 1, "a": 1, "p": 0.0874}, {"h": 2, "a": 1, "p": 0.0631}]}, {"num": 27, "date": "Jun 18, 2026", "time": "22:00", "home": "Canada", "away": "Qatar", "group": "B", "fifa_h": 1556.5, "fifa_a": 1455.0, "lh": 2.66, "la": 0.58, "pH": 0.81, "pD": 0.135, "pA": 0.055, "mode": [2, 0], "mode_p": 0.14, "rec": [2, 0], "rec_ev": 1.177, "expert": [4, 0], "top": [{"h": 2, "a": 0, "p": 0.1401}, {"h": 3, "a": 0, "p": 0.124}, {"h": 1, "a": 0, "p": 0.1019}, {"h": 4, "a": 0, "p": 0.0823}, {"h": 2, "a": 1, "p": 0.0807}, {"h": 3, "a": 1, "p": 0.0714}]}, {"num": 28, "date": "Jun 19, 2026", "time": "01:00", "home": "Mexico", "away": "Korea Republic", "group": "A", "fifa_h": 1681.0, "fifa_a": 1588.7, "lh": 1.76, "la": 1.06, "pH": 0.532, "pD": 0.248, "pA": 0.22, "mode": [1, 1], "mode_p": 0.118, "rec": [1, 0], "rec_ev": 0.862, "expert": [2, 1], "top": [{"h": 1, "a": 1, "p": 0.1179}, {"h": 1, "a": 0, "p": 0.0986}, {"h": 2, "a": 1, "p": 0.0979}, {"h": 2, "a": 0, "p": 0.0927}, {"h": 0, "a": 0, "p": 0.0665}, {"h": 1, "a": 2, "p": 0.0588}]}, {"num": 29, "date": "Jun 20, 2026", "time": "00:30", "home": "Brazil", "away": "Haiti", "group": "C", "fifa_h": 1761.2, "fifa_a": 1291.7, "lh": 4.06, "la": 0.18, "pH": 0.967, "pD": 0.03, "pA": 0.004, "mode": [4, 0], "mode_p": 0.173, "rec": [3, 0], "rec_ev": 1.34, "expert": [6, 0], "top": [{"h": 4, "a": 0, "p": 0.1726}, {"h": 3, "a": 0, "p": 0.1699}, {"h": 5, "a": 0, "p": 0.1403}, {"h": 2, "a": 0, "p": 0.1254}, {"h": 6, "a": 0, "p": 0.095}, {"h": 1, "a": 0, "p": 0.061}]}, {"num": 30, "date": "Jun 19, 2026", "time": "22:00", "home": "Scotland", "away": "Morocco", "group": "C", "fifa_h": 1498.3, "fifa_a": 1755.9, "lh": 0.38, "la": 1.54, "pH": 0.083, "pD": 0.257, "pA": 0.66, "mode": [0, 1], "mode_p": 0.221, "rec": [0, 1], "rec_ev": 1.176, "expert": [0, 1], "top": [{"h": 0, "a": 1, "p": 0.2213}, {"h": 0, "a": 2, "p": 0.174}, {"h": 0, "a": 0, "p": 0.1525}, {"h": 1, "a": 1, "p": 0.0908}, {"h": 0, "a": 3, "p": 0.0891}, {"h": 1, "a": 2, "p": 0.0658}]}, {"num": 31, "date": "Jun 20, 2026", "time": "03:00", "home": "United States", "away": "Australia", "group": "D", "fifa_h": 1673.1, "fifa_a": 1580.7, "lh": 1.76, "la": 0.61, "pH": 0.647, "pD": 0.236, "pA": 0.117, "mode": [1, 0], "mode_p": 0.159, "rec": [1, 0], "rec_ev": 1.071, "expert": [2, 0], "top": [{"h": 1, "a": 0, "p": 0.1594}, {"h": 2, "a": 0, "p": 0.1455}, {"h": 1, "a": 1, "p": 0.1061}, {"h": 0, "a": 0, "p": 0.1}, {"h": 2, "a": 1, "p": 0.0881}, {"h": 3, "a": 0, "p": 0.0853}]}, {"num": 32, "date": "Jun 19, 2026", "time": "19:00", "home": "Turkey", "away": "Paraguay", "group": "D", "fifa_h": 1599.0, "fifa_a": 1503.5, "lh": 1.3, "la": 1.04, "pH": 0.418, "pD": 0.293, "pA": 0.289, "mode": [1, 1], "mode_p": 0.138, "rec": [1, 0], "rec_ev": 0.758, "expert": [1, 1], "top": [{"h": 1, "a": 1, "p": 0.1379}, {"h": 1, "a": 0, "p": 0.1172}, {"h": 0, "a": 0, "p": 0.1038}, {"h": 0, "a": 1, "p": 0.092}, {"h": 2, "a": 1, "p": 0.0848}, {"h": 2, "a": 0, "p": 0.0815}]}, {"num": 33, "date": "Jun 20, 2026", "time": "20:00", "home": "Germany", "away": "Ivory Coast", "group": "E", "fifa_h": 1730.4, "fifa_a": 1533.0, "lh": 2.35, "la": 0.91, "pH": 0.689, "pD": 0.186, "pA": 0.124, "mode": [2, 0], "mode_p": 0.106, "rec": [2, 1], "rec_ev": 1.009, "expert": [3, 1], "top": [{"h": 2, "a": 0, "p": 0.1061}, {"h": 2, "a": 1, "p": 0.0967}, {"h": 1, "a": 1, "p": 0.0871}, {"h": 1, "a": 0, "p": 0.0852}, {"h": 3, "a": 0, "p": 0.0832}, {"h": 3, "a": 1, "p": 0.0759}]}, {"num": 34, "date": "Jun 21, 2026", "time": "00:00", "home": "Ecuador", "away": "Curaçao", "group": "E", "fifa_h": 1594.8, "fifa_a": 1294.7, "lh": 2.49, "la": 0.31, "pH": 0.847, "pD": 0.124, "pA": 0.029, "mode": [2, 0], "mode_p": 0.189, "rec": [2, 0], "rec_ev": 1.28, "expert": [3, 0], "top": [{"h": 2, "a": 0, "p": 0.1895}, {"h": 3, "a": 0, "p": 0.157}, {"h": 1, "a": 0, "p": 0.1496}, {"h": 4, "a": 0, "p": 0.0975}, {"h": 0, "a": 0, "p": 0.0642}, {"h": 2, "a": 1, "p": 0.0587}]}, {"num": 35, "date": "Jun 20, 2026", "time": "17:00", "home": "Netherlands", "away": "Sweden", "group": "F", "fifa_h": 1757.9, "fifa_a": 1514.8, "lh": 1.97, "la": 0.4, "pH": 0.747, "pD": 0.192, "pA": 0.061, "mode": [2, 0], "mode_p": 0.182, "rec": [1, 0], "rec_ev": 1.19, "expert": [2, 0], "top": [{"h": 2, "a": 0, "p": 0.1817}, {"h": 1, "a": 0, "p": 0.1802}, {"h": 3, "a": 0, "p": 0.1192}, {"h": 0, "a": 0, "p": 0.0982}, {"h": 1, "a": 1, "p": 0.0782}, {"h": 2, "a": 1, "p": 0.0726}]}, {"num": 36, "date": "Jun 21, 2026", "time": "04:00", "home": "Tunisia", "away": "Japan", "group": "F", "fifa_h": 1483.0, "fifa_a": 1660.4, "lh": 0.48, "la": 1.87, "pH": 0.082, "pD": 0.213, "pA": 0.705, "mode": [0, 1], "mode_p": 0.173, "rec": [0, 1], "rec_ev": 1.145, "expert": [0, 2], "top": [{"h": 0, "a": 1, "p": 0.1733}, {"h": 0, "a": 2, "p": 0.1667}, {"h": 0, "a": 3, "p": 0.1038}, {"h": 0, "a": 0, "p": 0.1006}, {"h": 1, "a": 1, "p": 0.0909}, {"h": 1, "a": 2, "p": 0.0802}]}, {"num": 37, "date": "Jun 21, 2026", "time": "22:00", "home": "Uruguay", "away": "Cape Verde", "group": "H", "fifa_h": 1673.1, "fifa_a": 1366.1, "lh": 2.49, "la": 0.3, "pH": 0.851, "pD": 0.122, "pA": 0.027, "mode": [2, 0], "mode_p": 0.192, "rec": [2, 0], "rec_ev": 1.287, "expert": [3, 0], "top": [{"h": 2, "a": 0, "p": 0.1921}, {"h": 3, "a": 0, "p": 0.1594}, {"h": 1, "a": 0, "p": 0.1515}, {"h": 4, "a": 0, "p": 0.0992}, {"h": 0, "a": 0, "p": 0.0647}, {"h": 2, "a": 1, "p": 0.0568}]}, {"num": 38, "date": "Jun 21, 2026", "time": "16:00", "home": "Spain", "away": "Saudi Arabia", "group": "H", "fifa_h": 1876.4, "fifa_a": 1421.4, "lh": 2.26, "la": 0.18, "pH": 0.85, "pD": 0.131, "pA": 0.019, "mode": [2, 0], "mode_p": 0.223, "rec": [2, 0], "rec_ev": 1.328, "expert": [2, 0], "top": [{"h": 2, "a": 0, "p": 0.2231}, {"h": 1, "a": 0, "p": 0.1952}, {"h": 3, "a": 0, "p": 0.1681}, {"h": 4, "a": 0, "p": 0.095}, {"h": 0, "a": 0, "p": 0.0894}, {"h": 5, "a": 0, "p": 0.043}]}, {"num": 39, "date": "Jun 21, 2026", "time": "19:00", "home": "Belgium", "away": "Iran", "group": "G", "fifa_h": 1734.7, "fifa_a": 1615.3, "lh": 2.25, "la": 0.57, "pH": 0.751, "pD": 0.174, "pA": 0.075, "mode": [2, 0], "mode_p": 0.15, "rec": [2, 0], "rec_ev": 1.129, "expert": [3, 0], "top": [{"h": 2, "a": 0, "p": 0.1504}, {"h": 1, "a": 0, "p": 0.1289}, {"h": 3, "a": 0, "p": 0.113}, {"h": 2, "a": 1, "p": 0.0865}, {"h": 1, "a": 1, "p": 0.0814}, {"h": 3, "a": 1, "p": 0.065}]}, {"num": 40, "date": "Jun 22, 2026", "time": "01:00", "home": "New Zealand", "away": "Egypt", "group": "G", "fifa_h": 1281.6, "fifa_a": 1563.2, "lh": 0.34, "la": 2.01, "pH": 0.048, "pD": 0.18, "pA": 0.772, "mode": [0, 2], "mode_p": 0.193, "rec": [0, 1], "rec_ev": 1.221, "expert": [0, 2], "top": [{"h": 0, "a": 2, "p": 0.1932}, {"h": 0, "a": 1, "p": 0.188}, {"h": 0, "a": 3, "p": 0.1296}, {"h": 0, "a": 0, "p": 0.0992}, {"h": 1, "a": 1, "p": 0.0689}, {"h": 1, "a": 2, "p": 0.0654}]}, {"num": 41, "date": "Jun 23, 2026", "time": "00:00", "home": "Norway", "away": "Senegal", "group": "I", "fifa_h": 1550.9, "fifa_a": 1689.0, "lh": 0.99, "la": 1.37, "pH": 0.264, "pD": 0.288, "pA": 0.448, "mode": [1, 1], "mode_p": 0.136, "rec": [0, 1], "rec_ev": 0.801, "expert": [1, 1], "top": [{"h": 1, "a": 1, "p": 0.1357}, {"h": 0, "a": 1, "p": 0.1214}, {"h": 0, "a": 0, "p": 0.1018}, {"h": 0, "a": 2, "p": 0.0885}, {"h": 1, "a": 2, "p": 0.0878}, {"h": 1, "a": 0, "p": 0.0857}]}, {"num": 42, "date": "Jun 22, 2026", "time": "20:00", "home": "France", "away": "Iraq", "group": "I", "fifa_h": 1877.3, "fifa_a": 1447.1, "lh": 3.13, "la": 0.18, "pH": 0.928, "pD": 0.064, "pA": 0.008, "mode": [3, 0], "mode_p": 0.189, "rec": [3, 0], "rec_ev": 1.335, "expert": [4, 0], "top": [{"h": 3, "a": 0, "p": 0.1895}, {"h": 2, "a": 0, "p": 0.1817}, {"h": 4, "a": 0, "p": 0.1482}, {"h": 1, "a": 0, "p": 0.1149}, {"h": 5, "a": 0, "p": 0.0927}, {"h": 6, "a": 0, "p": 0.0484}]}, {"num": 43, "date": "Jun 22, 2026", "time": "17:00", "home": "Argentina", "away": "Austria", "group": "J", "fifa_h": 1874.8, "fifa_a": 1593.5, "lh": 2.03, "la": 0.81, "pH": 0.653, "pD": 0.213, "pA": 0.134, "mode": [2, 0], "mode_p": 0.12, "rec": [1, 0], "rec_ev": 1.006, "expert": [2, 1], "top": [{"h": 2, "a": 0, "p": 0.1205}, {"h": 1, "a": 0, "p": 0.1127}, {"h": 1, "a": 1, "p": 0.1018}, {"h": 2, "a": 1, "p": 0.0976}, {"h": 3, "a": 0, "p": 0.0817}, {"h": 3, "a": 1, "p": 0.0662}]}, {"num": 44, "date": "Jun 23, 2026", "time": "03:00", "home": "Jordan", "away": "Algeria", "group": "J", "fifa_h": 1391.5, "fifa_a": 1564.3, "lh": 0.48, "la": 1.86, "pH": 0.083, "pD": 0.215, "pA": 0.703, "mode": [0, 1], "mode_p": 0.174, "rec": [0, 1], "rec_ev": 1.144, "expert": [0, 2], "top": [{"h": 0, "a": 1, "p": 0.1744}, {"h": 0, "a": 2, "p": 0.1666}, {"h": 0, "a": 3, "p": 0.1031}, {"h": 0, "a": 0, "p": 0.1019}, {"h": 1, "a": 1, "p": 0.0915}, {"h": 1, "a": 2, "p": 0.08}]}, {"num": 45, "date": "Jun 23, 2026", "time": "20:00", "home": "England", "away": "Ghana", "group": "L", "fifa_h": 1826.0, "fifa_a": 1346.3, "lh": 2.29, "la": 0.18, "pH": 0.854, "pD": 0.128, "pA": 0.018, "mode": [2, 0], "mode_p": 0.222, "rec": [2, 0], "rec_ev": 1.331, "expert": [2, 0], "top": [{"h": 2, "a": 0, "p": 0.2224}, {"h": 1, "a": 0, "p": 0.1925}, {"h": 3, "a": 0, "p": 0.1695}, {"h": 4, "a": 0, "p": 0.0969}, {"h": 0, "a": 0, "p": 0.0872}, {"h": 5, "a": 0, "p": 0.0443}]}, {"num": 46, "date": "Jun 23, 2026", "time": "23:00", "home": "Panama", "away": "Croatia", "group": "L", "fifa_h": 1540.6, "fifa_a": 1717.1, "lh": 0.49, "la": 1.88, "pH": 0.083, "pD": 0.213, "pA": 0.704, "mode": [0, 1], "mode_p": 0.171, "rec": [0, 1], "rec_ev": 1.141, "expert": [0, 2], "top": [{"h": 0, "a": 1, "p": 0.1711}, {"h": 0, "a": 2, "p": 0.1653}, {"h": 0, "a": 3, "p": 0.1033}, {"h": 0, "a": 0, "p": 0.0992}, {"h": 1, "a": 1, "p": 0.0915}, {"h": 1, "a": 2, "p": 0.081}]}, {"num": 47, "date": "Jun 23, 2026", "time": "17:00", "home": "Portugal", "away": "Uzbekistan", "group": "K", "fifa_h": 1763.8, "fifa_a": 1465.3, "lh": 2.94, "la": 0.32, "pH": 0.891, "pD": 0.089, "pA": 0.02, "mode": [2, 0], "mode_p": 0.168, "rec": [2, 0], "rec_ev": 1.285, "expert": [4, 0], "top": [{"h": 2, "a": 0, "p": 0.1676}, {"h": 3, "a": 0, "p": 0.1643}, {"h": 4, "a": 0, "p": 0.1208}, {"h": 1, "a": 0, "p": 0.1118}, {"h": 5, "a": 0, "p": 0.0711}, {"h": 2, "a": 1, "p": 0.0537}]}, {"num": 48, "date": "Jun 24, 2026", "time": "02:00", "home": "Colombia", "away": "DR Congo", "group": "K", "fifa_h": 1693.1, "fifa_a": 1478.3, "lh": 2.37, "la": 0.88, "pH": 0.699, "pD": 0.183, "pA": 0.118, "mode": [2, 0], "mode_p": 0.109, "rec": [2, 1], "rec_ev": 1.019, "expert": [3, 1], "top": [{"h": 2, "a": 0, "p": 0.109}, {"h": 2, "a": 1, "p": 0.0961}, {"h": 1, "a": 0, "p": 0.0871}, {"h": 3, "a": 0, "p": 0.0862}, {"h": 1, "a": 1, "p": 0.0859}, {"h": 3, "a": 1, "p": 0.076}]}, {"num": 49, "date": "Jun 24, 2026", "time": "22:00", "home": "Scotland", "away": "Brazil", "group": "C", "fifa_h": 1498.3, "fifa_a": 1761.2, "lh": 0.37, "la": 1.99, "pH": 0.055, "pD": 0.186, "pA": 0.759, "mode": [0, 2], "mode_p": 0.187, "rec": [0, 1], "rec_ev": 1.204, "expert": [0, 2], "top": [{"h": 0, "a": 2, "p": 0.1869}, {"h": 0, "a": 1, "p": 0.1833}, {"h": 0, "a": 3, "p": 0.1243}, {"h": 0, "a": 0, "p": 0.0982}, {"h": 1, "a": 1, "p": 0.0738}, {"h": 1, "a": 2, "p": 0.0694}]}, {"num": 50, "date": "Jun 24, 2026", "time": "22:00", "home": "Morocco", "away": "Haiti", "group": "C", "fifa_h": 1755.9, "fifa_a": 1291.7, "lh": 2.71, "la": 0.18, "pH": 0.897, "pD": 0.09, "pA": 0.012, "mode": [2, 0], "mode_p": 0.206, "rec": [2, 0], "rec_ev": 1.344, "expert": [3, 0], "top": [{"h": 2, "a": 0, "p": 0.2056}, {"h": 3, "a": 0, "p": 0.1855}, {"h": 1, "a": 0, "p": 0.1503}, {"h": 4, "a": 0, "p": 0.1255}, {"h": 5, "a": 0, "p": 0.068}, {"h": 0, "a": 0, "p": 0.0578}]}, {"num": 51, "date": "Jun 24, 2026", "time": "19:00", "home": "Switzerland", "away": "Canada", "group": "B", "fifa_h": 1649.4, "fifa_a": 1556.5, "lh": 1.31, "la": 1.05, "pH": 0.416, "pD": 0.292, "pA": 0.292, "mode": [1, 1], "mode_p": 0.138, "rec": [1, 0], "rec_ev": 0.755, "expert": [1, 1], "top": [{"h": 1, "a": 1, "p": 0.1378}, {"h": 1, "a": 0, "p": 0.1158}, {"h": 0, "a": 0, "p": 0.1024}, {"h": 0, "a": 1, "p": 0.0917}, {"h": 2, "a": 1, "p": 0.0849}, {"h": 2, "a": 0, "p": 0.0808}]}, {"num": 52, "date": "Jun 24, 2026", "time": "19:00", "home": "Bosnia and Herzegovina", "away": "Qatar", "group": "B", "fifa_h": 1385.8, "fifa_a": 1455.0, "lh": 1.53, "la": 0.82, "pH": 0.533, "pD": 0.273, "pA": 0.194, "mode": [1, 0], "mode_p": 0.139, "rec": [1, 0], "rec_ev": 0.923, "expert": [2, 0], "top": [{"h": 1, "a": 0, "p": 0.1386}, {"h": 1, "a": 1, "p": 0.1268}, {"h": 2, "a": 0, "p": 0.1116}, {"h": 0, "a": 0, "p": 0.1024}, {"h": 2, "a": 1, "p": 0.0916}, {"h": 0, "a": 1, "p": 0.071}]}, {"num": 53, "date": "Jun 25, 2026", "time": "01:00", "home": "Czech Republic", "away": "Mexico", "group": "A", "fifa_h": 1501.4, "fifa_a": 1681.0, "lh": 0.48, "la": 1.42, "pH": 0.118, "pD": 0.282, "pA": 0.6, "mode": [0, 1], "mode_p": 0.206, "rec": [0, 1], "rec_ev": 1.093, "expert": [0, 1], "top": [{"h": 0, "a": 1, "p": 0.2059}, {"h": 0, "a": 0, "p": 0.1549}, {"h": 0, "a": 2, "p": 0.151}, {"h": 1, "a": 1, "p": 0.108}, {"h": 1, "a": 2, "p": 0.0726}, {"h": 0, "a": 3, "p": 0.0717}]}, {"num": 54, "date": "Jun 25, 2026", "time": "01:00", "home": "South Africa", "away": "Korea Republic", "group": "A", "fifa_h": 1429.7, "fifa_a": 1588.7, "lh": 0.5, "la": 1.83, "pH": 0.088, "pD": 0.219, "pA": 0.694, "mode": [0, 1], "mode_p": 0.173, "rec": [0, 1], "rec_ev": 1.134, "expert": [0, 2], "top": [{"h": 0, "a": 1, "p": 0.1729}, {"h": 0, "a": 2, "p": 0.1635}, {"h": 0, "a": 0, "p": 0.1024}, {"h": 0, "a": 3, "p": 0.1}, {"h": 1, "a": 1, "p": 0.094}, {"h": 1, "a": 2, "p": 0.0814}]}, {"num": 55, "date": "Jun 25, 2026", "time": "20:00", "home": "Curaçao", "away": "Ivory Coast", "group": "E", "fifa_h": 1294.7, "fifa_a": 1533.0, "lh": 0.4, "la": 2.85, "pH": 0.029, "pD": 0.103, "pA": 0.868, "mode": [0, 2], "mode_p": 0.159, "rec": [0, 2], "rec_ev": 1.255, "expert": [0, 4], "top": [{"h": 0, "a": 2, "p": 0.1588}, {"h": 0, "a": 3, "p": 0.1511}, {"h": 0, "a": 1, "p": 0.1086}, {"h": 0, "a": 4, "p": 0.1078}, {"h": 1, "a": 2, "p": 0.0634}, {"h": 0, "a": 5, "p": 0.0616}]}, {"num": 56, "date": "Jun 25, 2026", "time": "20:00", "home": "Ecuador", "away": "Germany", "group": "E", "fifa_h": 1594.8, "fifa_a": 1730.4, "lh": 1.0, "la": 1.37, "pH": 0.266, "pD": 0.288, "pA": 0.446, "mode": [1, 1], "mode_p": 0.136, "rec": [0, 1], "rec_ev": 0.797, "expert": [1, 1], "top": [{"h": 1, "a": 1, "p": 0.1356}, {"h": 0, "a": 1, "p": 0.1202}, {"h": 0, "a": 0, "p": 0.1007}, {"h": 1, "a": 2, "p": 0.0879}, {"h": 0, "a": 2, "p": 0.0878}, {"h": 1, "a": 0, "p": 0.0855}]}, {"num": 57, "date": "Jun 25, 2026", "time": "23:00", "home": "Japan", "away": "Sweden", "group": "F", "fifa_h": 1660.4, "fifa_a": 1514.8, "lh": 1.38, "la": 0.98, "pH": 0.453, "pD": 0.288, "pA": 0.259, "mode": [1, 1], "mode_p": 0.135, "rec": [1, 0], "rec_ev": 0.81, "expert": [1, 1], "top": [{"h": 1, "a": 1, "p": 0.1355}, {"h": 1, "a": 0, "p": 0.1232}, {"h": 0, "a": 0, "p": 0.1027}, {"h": 2, "a": 0, "p": 0.0901}, {"h": 2, "a": 1, "p": 0.088}, {"h": 0, "a": 1, "p": 0.0851}]}, {"num": 58, "date": "Jun 25, 2026", "time": "23:00", "home": "Tunisia", "away": "Netherlands", "group": "F", "fifa_h": 1483.0, "fifa_a": 1757.9, "lh": 0.35, "la": 2.46, "pH": 0.034, "pD": 0.131, "pA": 0.834, "mode": [0, 2], "mode_p": 0.182, "rec": [0, 2], "rec_ev": 1.257, "expert": [0, 3], "top": [{"h": 0, "a": 2, "p": 0.1822}, {"h": 0, "a": 3, "p": 0.1494}, {"h": 0, "a": 1, "p": 0.145}, {"h": 0, "a": 4, "p": 0.0919}, {"h": 1, "a": 2, "p": 0.0644}, {"h": 0, "a": 0, "p": 0.0634}]}, {"num": 59, "date": "Jun 26, 2026", "time": "02:00", "home": "Turkey", "away": "United States", "group": "D", "fifa_h": 1599.0, "fifa_a": 1673.1, "lh": 1.53, "la": 1.74, "pH": 0.336, "pD": 0.243, "pA": 0.422, "mode": [1, 1], "mode_p": 0.107, "rec": [1, 2], "rec_ev": 0.707, "expert": [2, 2], "top": [{"h": 1, "a": 1, "p": 0.1075}, {"h": 1, "a": 2, "p": 0.088}, {"h": 2, "a": 1, "p": 0.0776}, {"h": 2, "a": 2, "p": 0.0674}, {"h": 0, "a": 1, "p": 0.0601}, {"h": 0, "a": 2, "p": 0.0574}]}, {"num": 60, "date": "Jun 26, 2026", "time": "02:00", "home": "Paraguay", "away": "Australia", "group": "D", "fifa_h": 1503.5, "fifa_a": 1580.7, "lh": 1.06, "la": 0.83, "pH": 0.398, "pD": 0.332, "pA": 0.271, "mode": [0, 0], "mode_p": 0.159, "rec": [0, 0], "rec_ev": 0.822, "expert": [1, 0], "top": [{"h": 0, "a": 0, "p": 0.1588}, {"h": 1, "a": 0, "p": 0.1526}, {"h": 1, "a": 1, "p": 0.1408}, {"h": 0, "a": 1, "p": 0.1168}, {"h": 2, "a": 0, "p": 0.0855}, {"h": 2, "a": 1, "p": 0.0707}]}, {"num": 61, "date": "Jun 26, 2026", "time": "19:00", "home": "Norway", "away": "France", "group": "I", "fifa_h": 1550.9, "fifa_a": 1877.3, "lh": 0.75, "la": 2.09, "pH": 0.116, "pD": 0.203, "pA": 0.68, "mode": [0, 2], "mode_p": 0.128, "rec": [0, 1], "rec_ev": 1.039, "expert": [1, 2], "top": [{"h": 0, "a": 2, "p": 0.1283}, {"h": 0, "a": 1, "p": 0.1171}, {"h": 1, "a": 1, "p": 0.0969}, {"h": 1, "a": 2, "p": 0.0957}, {"h": 0, "a": 3, "p": 0.0895}, {"h": 1, "a": 3, "p": 0.0668}]}, {"num": 62, "date": "Jun 26, 2026", "time": "19:00", "home": "Senegal", "away": "Iraq", "group": "I", "fifa_h": 1689.0, "fifa_a": 1447.1, "lh": 1.96, "la": 0.39, "pH": 0.747, "pD": 0.193, "pA": 0.06, "mode": [2, 0], "mode_p": 0.183, "rec": [1, 0], "rec_ev": 1.194, "expert": [2, 0], "top": [{"h": 2, "a": 0, "p": 0.183}, {"h": 1, "a": 0, "p": 0.1827}, {"h": 3, "a": 0, "p": 0.1194}, {"h": 0, "a": 0, "p": 0.1}, {"h": 1, "a": 1, "p": 0.0777}, {"h": 2, "a": 1, "p": 0.0717}]}, {"num": 63, "date": "Jun 27, 2026", "time": "03:00", "home": "Egypt", "away": "Iran", "group": "G", "fifa_h": 1563.2, "fifa_a": 1615.3, "lh": 1.11, "la": 1.25, "pH": 0.318, "pD": 0.295, "pA": 0.388, "mode": [1, 1], "mode_p": 0.139, "rec": [1, 1], "rec_ev": 0.728, "expert": [1, 1], "top": [{"h": 1, "a": 1, "p": 0.139}, {"h": 0, "a": 1, "p": 0.1107}, {"h": 0, "a": 0, "p": 0.1028}, {"h": 1, "a": 0, "p": 0.0971}, {"h": 1, "a": 2, "p": 0.0819}, {"h": 0, "a": 2, "p": 0.074}]}, {"num": 64, "date": "Jun 27, 2026", "time": "03:00", "home": "New Zealand", "away": "Belgium", "group": "G", "fifa_h": 1281.6, "fifa_a": 1734.7, "lh": 0.18, "la": 3.14, "pH": 0.008, "pD": 0.063, "pA": 0.929, "mode": [0, 3], "mode_p": 0.189, "rec": [0, 3], "rec_ev": 1.336, "expert": [0, 4], "top": [{"h": 0, "a": 3, "p": 0.1894}, {"h": 0, "a": 2, "p": 0.181}, {"h": 0, "a": 4, "p": 0.1487}, {"h": 0, "a": 1, "p": 0.1141}, {"h": 0, "a": 5, "p": 0.0933}, {"h": 0, "a": 6, "p": 0.0488}]}, {"num": 65, "date": "Jun 27, 2026", "time": "00:00", "home": "Cape Verde", "away": "Saudi Arabia", "group": "H", "fifa_h": 1366.1, "fifa_a": 1421.4, "lh": 1.1, "la": 1.26, "pH": 0.316, "pD": 0.294, "pA": 0.39, "mode": [1, 1], "mode_p": 0.139, "rec": [1, 1], "rec_ev": 0.727, "expert": [1, 1], "top": [{"h": 1, "a": 1, "p": 0.1388}, {"h": 0, "a": 1, "p": 0.1108}, {"h": 0, "a": 0, "p": 0.1024}, {"h": 1, "a": 0, "p": 0.0964}, {"h": 1, "a": 2, "p": 0.0822}, {"h": 0, "a": 2, "p": 0.0745}]}, {"num": 66, "date": "Jun 27, 2026", "time": "00:00", "home": "Uruguay", "away": "Spain", "group": "H", "fifa_h": 1673.1, "fifa_a": 1876.4, "lh": 0.47, "la": 1.48, "pH": 0.111, "pD": 0.272, "pA": 0.618, "mode": [0, 1], "mode_p": 0.204, "rec": [0, 1], "rec_ev": 1.108, "expert": [0, 1], "top": [{"h": 0, "a": 1, "p": 0.2038}, {"h": 0, "a": 2, "p": 0.1555}, {"h": 0, "a": 0, "p": 0.1475}, {"h": 1, "a": 1, "p": 0.1052}, {"h": 0, "a": 3, "p": 0.0768}, {"h": 1, "a": 2, "p": 0.0736}]}, {"num": 67, "date": "Jun 27, 2026", "time": "21:00", "home": "Panama", "away": "England", "group": "L", "fifa_h": 1540.6, "fifa_a": 1826.0, "lh": 0.35, "la": 2.93, "pH": 0.022, "pD": 0.093, "pA": 0.885, "mode": [0, 2], "mode_p": 0.163, "rec": [0, 2], "rec_ev": 1.275, "expert": [0, 4], "top": [{"h": 0, "a": 2, "p": 0.1635}, {"h": 0, "a": 3, "p": 0.1598}, {"h": 0, "a": 4, "p": 0.1172}, {"h": 0, "a": 1, "p": 0.1092}, {"h": 0, "a": 5, "p": 0.0687}, {"h": 1, "a": 2, "p": 0.0568}]}, {"num": 68, "date": "Jun 27, 2026", "time": "21:00", "home": "Croatia", "away": "Ghana", "group": "L", "fifa_h": 1717.1, "fifa_a": 1346.3, "lh": 1.68, "la": 0.66, "pH": 0.614, "pD": 0.25, "pA": 0.137, "mode": [1, 0], "mode_p": 0.156, "rec": [1, 0], "rec_ev": 1.033, "expert": [1, 1], "top": [{"h": 1, "a": 0, "p": 0.1556}, {"h": 2, "a": 0, "p": 0.136}, {"h": 1, "a": 1, "p": 0.1133}, {"h": 0, "a": 0, "p": 0.1029}, {"h": 2, "a": 1, "p": 0.0897}, {"h": 3, "a": 0, "p": 0.0761}]}, {"num": 69, "date": "Jun 28, 2026", "time": "02:00", "home": "Algeria", "away": "Austria", "group": "J", "fifa_h": 1564.3, "fifa_a": 1593.5, "lh": 1.14, "la": 1.67, "pH": 0.253, "pD": 0.257, "pA": 0.49, "mode": [1, 1], "mode_p": 0.122, "rec": [1, 2], "rec_ev": 0.812, "expert": [1, 2], "top": [{"h": 1, "a": 1, "p": 0.1218}, {"h": 1, "a": 2, "p": 0.0957}, {"h": 0, "a": 1, "p": 0.0943}, {"h": 0, "a": 2, "p": 0.0843}, {"h": 0, "a": 0, "p": 0.0676}, {"h": 2, "a": 1, "p": 0.0652}]}, {"num": 70, "date": "Jun 28, 2026", "time": "02:00", "home": "Jordan", "away": "Argentina", "group": "J", "fifa_h": 1391.5, "fifa_a": 1874.8, "lh": 0.18, "la": 3.2, "pH": 0.008, "pD": 0.06, "pA": 0.932, "mode": [0, 3], "mode_p": 0.189, "rec": [0, 3], "rec_ev": 1.339, "expert": [0, 4], "top": [{"h": 0, "a": 3, "p": 0.1891}, {"h": 0, "a": 2, "p": 0.1774}, {"h": 0, "a": 4, "p": 0.1512}, {"h": 0, "a": 1, "p": 0.1098}, {"h": 0, "a": 5, "p": 0.0967}, {"h": 0, "a": 6, "p": 0.0515}]}, {"num": 71, "date": "Jun 27, 2026", "time": "23:30", "home": "Colombia", "away": "Portugal", "group": "K", "fifa_h": 1693.1, "fifa_a": 1763.8, "lh": 1.1, "la": 1.29, "pH": 0.307, "pD": 0.291, "pA": 0.402, "mode": [1, 1], "mode_p": 0.138, "rec": [0, 1], "rec_ev": 0.729, "expert": [1, 1], "top": [{"h": 1, "a": 1, "p": 0.1377}, {"h": 0, "a": 1, "p": 0.1104}, {"h": 0, "a": 0, "p": 0.0992}, {"h": 1, "a": 0, "p": 0.0926}, {"h": 1, "a": 2, "p": 0.084}, {"h": 0, "a": 2, "p": 0.0765}]}, {"num": 72, "date": "Jun 27, 2026", "time": "23:30", "home": "DR Congo", "away": "Uzbekistan", "group": "K", "fifa_h": 1478.3, "fifa_a": 1465.3, "lh": 1.19, "la": 1.15, "pH": 0.36, "pD": 0.297, "pA": 0.343, "mode": [1, 1], "mode_p": 0.14, "rec": [1, 1], "rec_ev": 0.733, "expert": [1, 1], "top": [{"h": 1, "a": 1, "p": 0.1398}, {"h": 1, "a": 0, "p": 0.1067}, {"h": 0, "a": 0, "p": 0.1045}, {"h": 0, "a": 1, "p": 0.1032}, {"h": 2, "a": 1, "p": 0.0783}, {"h": 1, "a": 2, "p": 0.0759}]}], "fifa": {"Mexico": 1681.0, "South Africa": 1429.7, "Korea Republic": 1588.7, "Czech Republic": 1501.4, "Canada": 1556.5, "Bosnia and Herzegovina": 1385.8, "Qatar": 1455.0, "Switzerland": 1649.4, "Brazil": 1761.2, "Morocco": 1755.9, "Haiti": 1291.7, "Scotland": 1498.3, "United States": 1673.1, "Paraguay": 1503.5, "Australia": 1580.7, "Turkey": 1599.0, "Germany": 1730.4, "Curaçao": 1294.7, "Ivory Coast": 1533.0, "Ecuador": 1594.8, "Netherlands": 1757.9, "Japan": 1660.4, "Sweden": 1514.8, "Tunisia": 1483.0, "Belgium": 1734.7, "Egypt": 1563.2, "Iran": 1615.3, "New Zealand": 1281.6, "Spain": 1876.4, "Cape Verde": 1366.1, "Saudi Arabia": 1421.4, "Uruguay": 1673.1, "France": 1877.3, "Senegal": 1689.0, "Iraq": 1447.1, "Norway": 1550.9, "Argentina": 1874.8, "Algeria": 1564.3, "Austria": 1593.5, "Jordan": 1391.5, "Portugal": 1763.8, "DR Congo": 1478.3, "Uzbekistan": 1465.3, "Colombia": 1693.1, "England": 1826.0, "Croatia": 1717.1, "Ghana": 1346.3, "Panama": 1540.6}, "groups": {"A": ["Mexico", "South Africa", "Korea Republic", "Czech Republic"], "B": ["Canada", "Bosnia and Herzegovina", "Qatar", "Switzerland"], "C": ["Brazil", "Morocco", "Haiti", "Scotland"], "D": ["United States", "Paraguay", "Australia", "Turkey"], "E": ["Germany", "Curaçao", "Ivory Coast", "Ecuador"], "F": ["Netherlands", "Japan", "Sweden", "Tunisia"], "G": ["Belgium", "Egypt", "Iran", "New Zealand"], "H": ["Spain", "Cape Verde", "Saudi Arabia", "Uruguay"], "I": ["France", "Senegal", "Iraq", "Norway"], "J": ["Argentina", "Algeria", "Austria", "Jordan"], "K": ["Portugal", "DR Congo", "Uzbekistan", "Colombia"], "L": ["England", "Croatia", "Ghana", "Panama"]}, "scoring": {"exact": 3, "gd": 2, "dir": 1}, "generated": "2026-06-05"}